celery_debounce/__init__.py
celery_debounce/celery_debounce.py
celery_debounce/cli.py
celery_debounce-0.2.1.dist-info/AUTHORS.rst
celery_debounce-0.2.1.dist-info/LICENSE
celery_debounce-0.2.1.dist-info/METADATA
celery_debounce-0.2.1.dist-info/WHEEL
celery_debounce-0.2.1.dist-info/entry_points.txt
celery_debounce-0.2.1.dist-info/top_level.txt
celery_debounce-0.2.1.dist-info/RECORD
