Metadata-Version: 2.1
Name: celery-debounce
Version: 0.2.1
Summary: celery debounce without cache
Home-page: https://github.com/Concular/celery_debounce
Author: Concular GmbH
Author-email: amit@concular.com
License: UNKNOWN
Keywords: celery_debounce
Platform: UNKNOWN
Classifier: Development Status :: 2 - Pre-Alpha
Classifier: Intended Audience :: Developers
Classifier: Natural Language :: English
Classifier: Programming Language :: Python :: 3
Classifier: Programming Language :: Python :: 3.6
Classifier: Programming Language :: Python :: 3.7
Classifier: Programming Language :: Python :: 3.8
Requires-Python: >=3.6
License-File: LICENSE
License-File: AUTHORS.rst
Requires-Dist: Click (>=7.0)
Requires-Dist: celery (==5.2.7)
